bdcli/HELP.txt
bdcli/__init__.py
bdcli/bd.py
bdcli/key_token.py
bdcli/messages.py
bdcli/string_constants.py
bdcli/utils.py
bdcli-0.5.0.dist-info/LICENSE
bdcli-0.5.0.dist-info/METADATA
bdcli-0.5.0.dist-info/WHEEL
bdcli-0.5.0.dist-info/entry_points.txt
bdcli-0.5.0.dist-info/top_level.txt
bdcli-0.5.0.dist-info/RECORD
