Metadata-Version: 2.1
Name: bdcli
Version: 0.5.0
Summary: Python based command-line interface for Brown Dog services
Home-page: https://browndog.ncsa.illinois.edu/
Author: Kenton McHenry
Author-email: mchenry@illinois.edu
License: UNKNOWN
Download-URL: https://opensource.ncsa.illinois.edu/bitbucket/projects/BD/repos/bdcli
Keywords: Brown Dog, BD-CLI, BDCLI
Platform: UNKNOWN
Classifier: Development Status :: 4 - Beta
Classifier: Environment :: Console
Classifier: Intended Audience :: Developers
Classifier: Intended Audience :: Education
Classifier: Intended Audience :: Science/Research
Classifier: Intended Audience :: Information Technology
Classifier: Operating System :: MacOS :: MacOS X
Classifier: Operating System :: Microsoft :: Windows
Classifier: Operating System :: POSIX
Classifier: Programming Language :: Python :: 2.7
Requires-Dist: browndog (==0.5.0)
Requires-Dist: python-docker-machine (==0.2.2)
